mdtta/__init__.py
mdtta/__main__.py
mdtta/about.py
mdtta/base/__init__.py
mdtta/base/lzo.py
mdtta/base/pureSalsa20.py
mdtta/base/readmdict.py
mdtta/base/ripemd128.py
mdtta/base/writemdict.py
mdtta/chtml.py
mdtta/commands/__init__.py
mdtta/commands/base.py
mdtta/commands/convert.py
mdtta/commands/extract.py
mdtta/commands/info.py
mdtta/commands/keys.py
mdtta/commands/pack.py
mdtta/commands/query.py
mdtta/metadata.py
mdtta/reader.py
mdtta/writer.py
mdtta-2.0.2.dist-info/WHEEL
mdtta-2.0.2.dist-info/entry_points.txt
mdtta-2.0.2.dist-info/METADATA
mdtta-2.0.2.dist-info/RECORD
