Metadata-Version: 2.3
Name: mdtta
Version: 2.0.2
Summary: MDx Dict Trans ToolKit
Keywords: mdict,dictionary,mdx,mdd,pack,unpack
Author: Libukai
Author-email: Libukai <xiaobuyao@gmail.com>
License: MIT
Classifier: Development Status :: 4 - Beta
Classifier: Intended Audience :: Developers
Classifier: Topic :: Text Processing :: Linguistic
Classifier: License :: OSI Approved :: MIT License
Classifier: Programming Language :: Python :: 3
Classifier: Programming Language :: Python :: 3.13
Classifier: Operating System :: OS Independent
Requires-Dist: tomli-w>=1.2.0
Requires-Dist: tqdm>=4.64.1
Requires-Dist: xxhash>=3.2.0
Requires-Python: 
Project-URL: Bug Tracker, https://github.com/likai/mdtt/issues
Project-URL: Documentation, https://github.com/likai/mdtt#readme
Project-URL: Homepage, https://github.com/likai/mdtt
